article_extractor/__init__.py
article_extractor/cache.py
article_extractor/candidate_finder.py
article_extractor/cli.py
article_extractor/concurrency_limiter.py
article_extractor/constants.py
article_extractor/content_sanitizer.py
article_extractor/crawl_job_store.py
article_extractor/crawler.py
article_extractor/discovery.py
article_extractor/document_cleaner.py
article_extractor/dom_utils.py
article_extractor/extraction_cache.py
article_extractor/extractor.py
article_extractor/fetcher.py
article_extractor/lru_cache.py
article_extractor/network.py
article_extractor/observability.py
article_extractor/rate_limiter.py
article_extractor/request_logger.py
article_extractor/retry_utils.py
article_extractor/scorer.py
article_extractor/server.py
article_extractor/settings.py
article_extractor/sitemap_parser.py
article_extractor/storage.py
article_extractor/storage_queue.py
article_extractor/title_extractor.py
article_extractor/types.py
article_extractor/url_normalizer.py
article_extractor/utils.py
article_extractor-0.5.5.dist-info/METADATA
article_extractor-0.5.5.dist-info/WHEEL
article_extractor-0.5.5.dist-info/entry_points.txt
article_extractor-0.5.5.dist-info/licenses/LICENSE
article_extractor-0.5.5.dist-info/RECORD
