Metadata-Version: 2.4
Name: article-extractor
Version: 0.5.5
Summary: Pure-Python article extraction library and HTTP service - Drop-in replacement for readability-js-server
Project-URL: Homepage, https://github.com/pankaj28843/article-extractor
Project-URL: Repository, https://github.com/pankaj28843/article-extractor
Author-email: Pankaj Kumar Singh <pankaj28843@gmail.com>
License: MIT
License-File: LICENSE
Keywords: article,extraction,html,markdown,readability
Classifier: Development Status :: 4 - Beta
Classifier: Intended Audience :: Developers
Classifier: License :: OSI Approved :: MIT License
Classifier: Programming Language :: Python :: 3
Classifier: Programming Language :: Python :: 3.12
Classifier: Programming Language :: Python :: 3.13
Classifier: Programming Language :: Python :: 3.14
Classifier: Topic :: Text Processing :: Markup :: HTML
Requires-Python: >=3.12
Requires-Dist: defusedxml>=0.7.1
Requires-Dist: justhtml>=0.40.0
Requires-Dist: pydantic-settings>=2.12.0
Requires-Dist: pydantic>=2.12.5
Provides-Extra: all
Requires-Dist: fake-useragent>=2.2.0; extra == 'all'
Requires-Dist: fastapi>=0.128.0; extra == 'all'
Requires-Dist: httpx>=0.28.1; extra == 'all'
Requires-Dist: playwright>=1.57.0; extra == 'all'
Requires-Dist: uvicorn[standard]>=0.40.0; extra == 'all'
Provides-Extra: docs
Requires-Dist: mkdocs>=1.6.1; extra == 'docs'
Provides-Extra: httpx
Requires-Dist: httpx>=0.28.1; extra == 'httpx'
Provides-Extra: playwright
Requires-Dist: playwright>=1.57.0; extra == 'playwright'
Provides-Extra: server
Requires-Dist: fake-useragent>=2.2.0; extra == 'server'
Requires-Dist: fastapi>=0.128.0; extra == 'server'
Requires-Dist: httpx>=0.28.1; extra == 'server'
Requires-Dist: uvicorn[standard]>=0.40.0; extra == 'server'
Provides-Extra: ua
Requires-Dist: fake-useragent>=2.2.0; extra == 'ua'
